google/iam/v1/__init__.py
google/iam/v1/iam_policy.proto
google/iam/v1/iam_policy_pb2.py
google/iam/v1/iam_policy_pb2_grpc.py
google/iam/v1/options.proto
google/iam/v1/options_pb2.py
google/iam/v1/options_pb2_grpc.py
google/iam/v1/policy.proto
google/iam/v1/policy_pb2.py
google/iam/v1/policy_pb2_grpc.py
google/iam/v1/logging/__init__.py
google/iam/v1/logging/audit_data.proto
google/iam/v1/logging/audit_data_pb2.py
grpc_google_iam_v1-0.13.0.dist-info/LICENSE
grpc_google_iam_v1-0.13.0.dist-info/METADATA
grpc_google_iam_v1-0.13.0.dist-info/WHEEL
grpc_google_iam_v1-0.13.0.dist-info/top_level.txt
grpc_google_iam_v1-0.13.0.dist-info/RECORD
