Metadata-Version: 2.1
Name: grpc-google-iam-v1
Version: 0.13.0
Summary: IAM API client library
Home-page: https://github.com/googleapis/python-grpc-google-iam-v1
Author: Google LLC
Author-email: googleapis-packages@google.com
License: Apache 2.0
Platform: Posix; MacOS X; Windows
Classifier: Development Status :: 4 - Beta
Classifier: Intended Audience :: Developers
Classifier: License :: OSI Approved :: Apache Software License
Classifier: Programming Language :: Python
Classifier: Programming Language :: Python :: 3
Classifier: Programming Language :: Python :: 3.7
Classifier: Programming Language :: Python :: 3.8
Classifier: Programming Language :: Python :: 3.9
Classifier: Programming Language :: Python :: 3.10
Classifier: Programming Language :: Python :: 3.11
Classifier: Programming Language :: Python :: 3.12
Classifier: Operating System :: OS Independent
Classifier: Topic :: Internet
Requires-Python: >=3.7
License-File: LICENSE
Requires-Dist: grpcio<2.0.0dev,>=1.44.0
Requires-Dist: googleapis-common-protos[grpc]<2.0.0dev,>=1.56.0
Requires-Dist: protobuf!=3.20.0,!=3.20.1,!=4.21.1,!=4.21.2,!=4.21.3,!=4.21.4,!=4.21.5,<5.0.0dev,>=3.19.5
